.codespellignore
.gitignore
.pre-commit-config.yaml
.readthedocs.yaml
CHANGELOG.rst
CITATION.cff
LICENSE
MANIFEST.in
README.md
codecov.yaml
pyproject.toml
pytest.ini
.github/dependabot.yml
.github/pull_request_template.md
.github/ISSUE_TEMPLATE/bug_report.md
.github/ISSUE_TEMPLATE/documentation-improvement.md
.github/ISSUE_TEMPLATE/feature_request.md
.github/workflows/binder.yaml
.github/workflows/ci.yaml
.github/workflows/ci_fixed.yaml
.github/workflows/python-publish.yaml
changelog/567.feature.rst
changelog/571.feature.rst
changelog/572.feature.rst
changelog/573.breaking.rst
changelog/574.bugfix.rst
changelog/574.feature.rst
changelog/576.feature.rst
changelog/577.trivial.rst
changelog/580.feature.rst
changelog/583.doc.rst
changelog/README.rst
docs/Makefile
docs/conf.py
docs/contribute.rst
docs/help.rst
docs/index.rst
docs/intro.rst
docs/_static/favicon.ico
docs/_static/logo.png
docs/binder/requirements.txt
docs/binder/runtime.txt
docs/data/access.rst
docs/data/data_anomalies.rst
docs/data/data_codes.rst
docs/data/data_object.rst
docs/data/data_overview.rst
docs/data/data_versions.rst
docs/data/index.rst
docs/data/metadata.rst
docs/images/PUNCH_data_flow.png
docs/pipeline/design.rst
docs/pipeline/index.rst
docs/pipeline/overview.rst
docs/pipeline/level1/deficient_pixel.rst
docs/pipeline/level1/despike.rst
docs/pipeline/level1/destreak.rst
docs/pipeline/level1/index.rst
docs/pipeline/level1/initial_uncertainty.rst
docs/pipeline/level1/pointing.rst
docs/pipeline/level1/psf_correction.rst
docs/pipeline/level1/quartic_fit.rst
docs/pipeline/level1/stray_light.rst
docs/pipeline/level2/bright_structure.rst
docs/pipeline/level2/image_merging.rst
docs/pipeline/level2/image_resample.rst
docs/pipeline/level2/index.rst
docs/pipeline/level2/polarization.rst
docs/pipeline/level3/f_corona.rst
docs/pipeline/level3/index.rst
docs/pipeline/level3/low_noise.rst
docs/pipeline/level3/polarization.rst
docs/pipeline/level3/starfield.rst
docs/pipeline/level3/velocity.rst
punchbowl.egg-info/PKG-INFO
punchbowl.egg-info/SOURCES.txt
punchbowl.egg-info/dependency_links.txt
punchbowl.egg-info/entry_points.txt
punchbowl.egg-info/requires.txt
punchbowl.egg-info/top_level.txt
