Metadata-Version: 2.4
Name: punchbowl
Version: 0.0.19
Summary: PUNCH science calibration code
Author-email: "J. Marcus Hughes" <marcus.hughes@swri.org>, Chris Lowder <chris.lowder@swri.org>, Matthew West <matthew.west@swri.org>, Sarak Kovac <sarah.kovac@swri.org>, Ritesh Patel <ritesh.patel@swri.org>, Derek Lamb <derek.lamb@swri.org>, Dan Seaton <daniel.seaton@swri.org>
Maintainer-email: "J. Marcus Hughes" <marcus.hughes@swri.org>
License: Copyright (c) 2024 PUNCH Science Operations Center
Project-URL: Documentation, https://punchbowl.readthedocs.io/en/latest/
Project-URL: Repository, https://github.com/punch-mission/punchbowl.git
Project-URL: Bug Tracker, https://github.com/punch-mission/punchbowl/issues
Keywords: solar physics,PUNCH,NASA,science,calibration
Classifier: Development Status :: 4 - Beta
Classifier: Programming Language :: Python
Requires-Python: >=3.11
License-File: LICENSE
Requires-Dist: numpy
Requires-Dist: astropy
Requires-Dist: sunpy[all]
Requires-Dist: pandas
Requires-Dist: ndcube
Requires-Dist: matplotlib<=3.9.2
Requires-Dist: ccsdspy
Requires-Dist: prefect[dask]
Requires-Dist: regularizepsf
Requires-Dist: solpolpy
Requires-Dist: scipy
Requires-Dist: lmfit
Requires-Dist: sunkit-image
Requires-Dist: setuptools
Requires-Dist: reproject
Requires-Dist: pylibjpeg
Requires-Dist: python-dateutil
Requires-Dist: remove_starfield>=0.0.4
Requires-Dist: quadprog
Requires-Dist: pylibjpeg[openjpeg]
Requires-Dist: requests
Requires-Dist: threadpoolctl
Requires-Dist: numexpr
Requires-Dist: glymur
Requires-Dist: astroscrappy
Requires-Dist: scikit-learn
Requires-Dist: astrometry
Requires-Dist: numba
Provides-Extra: test
Requires-Dist: pytest; extra == "test"
Requires-Dist: pytest-order; extra == "test"
Requires-Dist: codespell; extra == "test"
Requires-Dist: coverage; extra == "test"
Requires-Dist: pytest-cov; extra == "test"
Requires-Dist: flake8; extra == "test"
Requires-Dist: pytest-runner; extra == "test"
Requires-Dist: pytest-mpl; extra == "test"
Requires-Dist: pre-commit; extra == "test"
Requires-Dist: ruff; extra == "test"
Requires-Dist: hypothesis; extra == "test"
Provides-Extra: docs
Requires-Dist: astroid>=3; extra == "docs"
Requires-Dist: sphinx; extra == "docs"
Requires-Dist: sphinx-gallery; extra == "docs"
Requires-Dist: sphinx_rtd_theme; extra == "docs"
Requires-Dist: codespell; extra == "docs"
Requires-Dist: packaging; extra == "docs"
Requires-Dist: pydata-sphinx-theme; extra == "docs"
Requires-Dist: sphinx-autoapi; extra == "docs"
Requires-Dist: sphinx-favicon; extra == "docs"
Requires-Dist: jupyterlite-sphinx; extra == "docs"
Requires-Dist: ipython; extra == "docs"
Requires-Dist: ipykernel; extra == "docs"
Requires-Dist: sphinxcontrib-mermaid; extra == "docs"
Provides-Extra: gpu
Requires-Dist: cupy; extra == "gpu"
Provides-Extra: dev
Requires-Dist: punchbowl[docs,test]; extra == "dev"
Dynamic: license-file
